mkdocs_exclude_tagged_files/__init__.py
mkdocs_exclude_tagged_files/plugin.py
mkdocs_exclude_tagged_files-1.0.4.dist-info/LICENSE.md
mkdocs_exclude_tagged_files-1.0.4.dist-info/METADATA
mkdocs_exclude_tagged_files-1.0.4.dist-info/WHEEL
mkdocs_exclude_tagged_files-1.0.4.dist-info/entry_points.txt
mkdocs_exclude_tagged_files-1.0.4.dist-info/top_level.txt
mkdocs_exclude_tagged_files-1.0.4.dist-info/RECORD
