Metadata-Version: 2.1
Name: mkdocs-exclude-tagged-files
Version: 1.0.4
Summary: A mkdocs plugin that excludes files based on a list of frontmatter tags from being included in the final mkdocs output.
Home-page: https://github.com/JonasDoesThings/mkdocs-exclude-tagged-files
Author: Jonas Lorenz <jonas@jonasdoesthings.com>
Author-email: jonas@jonasdoesthings.com
License: MIT
Keywords: mkdocs,mkdocs-plugin
License-File: LICENSE.md
Requires-Dist: mkdocs
Requires-Dist: python-frontmatter
Requires-Dist: charset-normalizer
